{
  "General": "عام",
  "Toast": "نخب",
  "Tools": "أدوات",
  "Capture": "التقاط",
  "Recording": "التسجيل",
  "OCR": "التعرف الضوئي على الحروف",
  "History": "التاريخ",
  "Uploads": "التحميلات",
  "About": "حول",
  "Sound & Motion": "الصوت والحركة",
  "Language": "اللغة",
  "Interface language": "لغة الواجهة",
  "Auto (system language)": "تلقائي (لغة النظام)",
  "Auto (interface/system language)": "تلقائي (الواجهة/لغة النظام)",
  "Auto-detect": "الكشف التلقائي",
  "English": "الإنجليزية",
  "Hebrew": "العبرية",
  "Mute capture sounds": "كتم أصوات الالتقاط",
  "Disable animations": "تعطيل الرسوم المتحركة",
  "Sound pack": "حزمة الصوت",
  "Default": "الافتراضي",
  "Soft": "ناعم",
  "Retro": "الرجعية",
  "Search": "بحث",
  "Show image search bar": "إظهار شريط البحث عن الصور",
  "Auto-index images": "الصور الفهرسة التلقائية",
  "Show search diagnostics": "عرض تشخيصات البحث",
  "Image index cache": "ذاكرة التخزين المؤقت لفهرس الصور",
  "Reset": "إعادة تعيين",
  "Capture Tool": "أداة الالتقاط",
  "Default capture tool": "أداة الالتقاط الافتراضية",
  "Center aspect ratio": "Center aspect ratio",
  "Free": "Free",
  "Square": "Square",
  "Rectangle": "مستطيل",
  "Center": "Center",
  "Freeform": "شكل حر",
  "Overlay": "تراكب",
  "Span selection overlay across all monitors": "Span selection overlay across all monitors",
  "Show pixel magnifier while selecting": "Show pixel magnifier while selecting",
  "Show cursor in captures and recordings": "Show cursor in captures and recordings",
  "Selection overlay": "Selection overlay",
  "Show cursor in captures": "إظهار المؤشر في اللقطات",
  "Show crosshair guides": "إظهار أدلة التقاطع",
  "Show pixel magnifier": "إظهار مكبر البكسل",
  "Span screenshot overlay across all monitors": "قم بتوسيع تراكب لقطة الشاشة عبر جميع الشاشات",
  "Annotation stroke and shadow": "السكتة الدماغية والظل الشرح",
  "Behavior": "السلوك",
  "Window detection": "كشف النافذة",
  "Off": "إيقاف",
  "Windows only": "ويندوز فقط",
  "Capture dock": "القبض على قفص الاتهام",
  "Top": "أعلى",
  "Bottom": "أسفل",
  "Left": "اليسار",
  "Right": "صحيح",
  "After capture": "بعد القبض",
  "Copy to clipboard": "نسخ إلى الحافظة",
  "Preview + Copy": "معاينة + نسخ",
  "Preview only": "معاينة فقط",
  "Capture delay": "تأخير الالتقاط",
  "None": "لا شيء",
  "3 seconds": "3 ثواني",
  "5 seconds": "5 ثواني",
  "10 seconds": "10 ثواني",
  "Saving": "الادخار",
  "Save screenshots to file": "حفظ لقطات الشاشة إلى ملف",
  "Ask for file name every time": "اسأل عن اسم الملف في كل مرة",
  "File name pattern": "نمط اسم الملف",
  "Preview:": "معاينة:",
  "Create monthly subfolders": "إنشاء مجلدات فرعية شهرية",
  "Save folder": "حفظ المجلد",
  "Browse": "تصفح",
  "Default format": "التنسيق الافتراضي",
  "JPG quality": "جودة JPG",
  "Max image size": "الحد الأقصى لحجم الصورة",
  "Original": "أصلي",
  "Save capture history": "حفظ تاريخ الالتقاط",
  "Auto-clear history": "مسح التاريخ تلقائيًا",
  "Never": "أبدا",
  "1 day": "يوم واحد",
  "7 days": "7 أيام",
  "30 days": "30 يوما",
  "3 months": "3 أشهر",
  "Format": "التنسيق",
  "Quality": "الجودة",
  "Show cursor in recordings": "إظهار المؤشر في التسجيلات",
  "Audio": "الصوت",
  "Record microphone": "سجل الميكروفون",
  "Record desktop audio": "تسجيل صوت سطح المكتب",
  "Recognition": "الاعتراف",
  "OCR language": "لغة التعرف الضوئي على الحروف",
  "Translation": "الترجمة",
  "Default source language": "لغة المصدر الافتراضية",
  "Default target language": "اللغة الهدف الافتراضية",
  "Translation engine": "محرك الترجمة",
  "Engines": "محركات",
  "Open-source Local": "مفتوح المصدر محلي",
  "Install": "تثبيت",
  "Checking install state...": "جارٍ التحقق من حالة التثبيت...",
  "Placement": "التنسيب",
  "Toast position": "موقف التوست",
  "Top Left": "أعلى اليسار",
  "Top Right": "أعلى اليمين",
  "Duration": "المدة",
  "Fade out": "تتلاشى",
  "Button layout": "تخطيط الزر",
  "Updates": "التحديثات",
  "Automatically check for updates": "التحقق تلقائيا من وجود تحديثات",
  "Checking for updates...": "جارٍ التحقق من وجود تحديثات...",
  "Check now": "تحقق الآن",
  "Open release": "الافراج المفتوح",
  "Links": "روابط",
  "Source Code": "كود المصدر",
  "Releases": "الإصدارات",
  "Issues": "القضايا",
  "License": "الترخيص",
  "Launch on startup": "إطلاق عند بدء التشغيل",
  "Reset Settings": "إعادة ضبط الإعدادات",
  "Uninstall OddSnap": "إلغاء تثبيت OddSnap",
  "Export settings": "إعدادات التصدير",
  "Import settings": "إعدادات الاستيراد",
  "Select": "اختر",
  "Clear all": "مسح الكل",
  "Delete selected": "حذف المحدد",
  "Images": "الصور",
  "Text": "نص",
  "Videos/GIFs": "مقاطع الفيديو/صور GIF",
  "Colors": "الألوان",
  "Stickers": "ملصقات",
  "Screenshot": "لقطة الشاشة",
  "Color picker": "منتقي الألوان",
  "Record": "سجل",
  "Stop recording": "توقف عن التسجيل",
  "Scroll capture": "التقاط التمرير",
  "Settings": "الإعدادات",
  "Quit": "استقال",
  "OddSnap - Click to capture, right-click for menu": "OddSnap - انقر للالتقاط، وانقر بزر الماوس الأيمن للوصول إلى القائمة",
  "OddSnap recording - click to stop, right-click for menu": "تسجيل OddSnap - انقر للإيقاف، ثم انقر بزر الماوس الأيمن للوصول إلى القائمة",
  "OddSnap ready": "OddSnap جاهز",
  "Settings exported": "تم تصدير الإعدادات",
  "Settings imported": "تم استيراد الإعدادات",
  "Settings have been applied.": "تم تطبيق الإعدادات.",
  "Import failed": "فشل الاستيراد",
  "Export failed": "فشل التصدير",
  "Cancel": "إلغاء",
  "Copied": "منقول",
  "Copied translation": "الترجمة المنسوخة",
  "Delete": "حذف",
  "Translate": "ترجمة",
  "Translating...": "ترجمة...",
  "Copy result": "نسخ النتيجة",
  "Copy text": "نسخ النص",
  "Local model": "النموذج المحلي",
  "Argos (offline)": "أرغوس (غير متصل)",
  "Google Translate": "ترجمة جوجل",
  "Warming local model...": "نموذج محلي دافئ...",
  "Starting translation...": "جارٍ بدء الترجمة...",
  "Detecting language...": "كشف اللغة...",
  "Sending text...": "جارٍ إرسال النص...",
  "Generating translation...": "جارٍ إنشاء الترجمة...",
  "Still working locally...": "لا يزال يعمل محليا ...",
  "Finishing translation...": "الانتهاء من الترجمة...",
  "More tools": "المزيد من الأدوات",
  "Color": "اللون",
  "Close (Esc)": "إغلاق (خروج)",
  "Save edits": "Save edits",
  "Capture tools": "أدوات الالتقاط",
  "Capture actions": "التقاط الإجراءات",
  "Annotation tools": "أدوات التعليقات التوضيحية",
  "Fullscreen capture": "التقاط ملء الشاشة",
  "Active window": "نافذة نشطة",
  "Rectangle Select": "تحديد المستطيل",
  "Center Select": "Center Select",
  "Freeform Select": "تحديد الشكل الحر",
  "Sticker": "ملصق",
  "Upscale": "الراقي",
  "QR/Barcode": "QR/الباركود",
  "Arrow": "السهم",
  "Curved Arrow": "السهم المنحني",
  "Highlight": "تسليط الضوء",
  "Blur": "طمس",
  "Step Number": "رقم الخطوة",
  "Magnifier": "Magnifier",
  "Draw": "ارسم",
  "Line": "الخط",
  "Ruler": "حاكم",
  "Circle": "دائرة",
  "Emoji": "الرموز التعبيرية",
  "Eraser": "ممحاة",
  "Press keys...": "اضغط على المفاتيح...",
  "Yes": "نعم",
  "No": "لا",
  "Saved": "تم الحفظ",
  "Save failed": "فشل الحفظ",
  "Deleted": "تم الحذف",
  "Delete failed": "فشل الحذف",
  "Hotkey conflict": "صراع مفتاح التشغيل السريع",
  "Capture error": "التقاط الخطأ",
  "Recording error": "خطأ في التسجيل",
  "Scroll capture error": "خطأ في التقاط التمرير",
  "OCR error": "خطأ في التعرف الضوئي على الحروف",
  "Sticker failed": "فشل الملصق",
  "Upscale failed": "الراقي فشل",
  "Scan failed": "فشل المسح",
  "No QR/barcode found": "لم يتم العثور على QR/الرمز الشريطي",
  "QR Code copied": "تم نسخ رمز الاستجابة السريعة",
  "Barcode copied": "تم نسخ الباركود",
  "Color copied": "اللون منسوخ",
  "Screenshot ready": "لقطة الشاشة جاهزة",
  "Sticker copied": "تم نسخ الملصق",
  "Sticker ready": "الملصق جاهز",
  "Upscale copied": "منقول راقي",
  "Upscale ready": "راقية جاهزة",
  "Upload error": "خطأ في التحميل",
  "Upload failed": "فشل التحميل",
  "Upload works": "أعمال التحميل",
  "Uploaded": "تم الرفع",
  "Upload not configured": "لم يتم تكوين التحميل",
  "Update available": "التحديث متاح",
  "Update failed": "فشل التحديث",
  "Update check failed": "فشل التحقق من التحديث",
  "OddSnap is up to date": "OddSnap محدث"
}
